odoo9_addon_delivery_carrier_label_postlogistics-9.0.1.1.1-py2.7-nspkg.pth
odoo9_addon_delivery_carrier_label_postlogistics-9.0.1.1.1.dist-info/METADATA
odoo9_addon_delivery_carrier_label_postlogistics-9.0.1.1.1.dist-info/RECORD
odoo9_addon_delivery_carrier_label_postlogistics-9.0.1.1.1.dist-info/WHEEL
odoo9_addon_delivery_carrier_label_postlogistics-9.0.1.1.1.dist-info/namespace_packages.txt
odoo9_addon_delivery_carrier_label_postlogistics-9.0.1.1.1.dist-info/top_level.txt
odoo_addons/delivery_carrier_label_postlogistics/README.rst
odoo_addons/delivery_carrier_label_postlogistics/__init__.py
odoo_addons/delivery_carrier_label_postlogistics/__openerp__.py
odoo_addons/delivery_carrier_label_postlogistics/data/barcode_v2_1.wsdl
odoo_addons/delivery_carrier_label_postlogistics/data/barcode_v2_1.xsd
odoo_addons/delivery_carrier_label_postlogistics/data/barcode_v2_2.wsdl
odoo_addons/delivery_carrier_label_postlogistics/data/barcode_v2_2.xsd
odoo_addons/delivery_carrier_label_postlogistics/data/delivery.xml
odoo_addons/delivery_carrier_label_postlogistics/data/post-barcode-handbuch.pdf
odoo_addons/delivery_carrier_label_postlogistics/data/res_partner.xml
odoo_addons/delivery_carrier_label_postlogistics/data/integration/barcode_v2_2_wsbc.wsdl
odoo_addons/delivery_carrier_label_postlogistics/data/integration/barcode_v2_2_wsbc.xsd
odoo_addons/delivery_carrier_label_postlogistics/data/production/barcode_v2_2_wsbc.wsdl
odoo_addons/delivery_carrier_label_postlogistics/data/production/barcode_v2_2_wsbc.xsd
odoo_addons/delivery_carrier_label_postlogistics/i18n/am.po
odoo_addons/delivery_carrier_label_postlogistics/i18n/ar.po
odoo_addons/delivery_carrier_label_postlogistics/i18n/bg.po
odoo_addons/delivery_carrier_label_postlogistics/i18n/bs.po
odoo_addons/delivery_carrier_label_postlogistics/i18n/ca.po
odoo_addons/delivery_carrier_label_postlogistics/i18n/ca_ES.po
odoo_addons/delivery_carrier_label_postlogistics/i18n/cs.po
odoo_addons/delivery_carrier_label_postlogistics/i18n/da.po
odoo_addons/delivery_carrier_label_postlogistics/i18n/da_DK.po
odoo_addons/delivery_carrier_label_postlogistics/i18n/de.po
odoo_addons/delivery_carrier_label_postlogistics/i18n/delivery_carrier_label_postlogistics.pot
odoo_addons/delivery_carrier_label_postlogistics/i18n/el_GR.po
odoo_addons/delivery_carrier_label_postlogistics/i18n/en_AU.po
